fastnsa/__init__.py
fastnsa/__init__.pyi
fastnsa/bindings/__init__.py
fastnsa/bindings/_lib.py
fastnsa/bindings/capi.py
fastnsa/bindings/libfastnsa.so
fastnsa/core/__init__.py
fastnsa/core/events.py
fastnsa/core/network.py
fastnsa/core/types.py
fastnsa/io/__init__.py
fastnsa/io/network.py
fastnsa/io/points.py
fastnsa/pipeline/__init__.py
fastnsa/pipeline/preprocess.py
fastnsa/stats/__init__.py
fastnsa/stats/k_function.py
fastnsa/utils/__init__.py
fastnsa-0.1.0.dist-info/licenses/LICENSE
fastnsa-0.1.0.dist-info/METADATA
fastnsa-0.1.0.dist-info/WHEEL
fastnsa-0.1.0.dist-info/top_level.txt
fastnsa-0.1.0.dist-info/RECORD
