Metadata-Version: 2.4
Name: fastnsa
Version: 0.1.0
Summary: High-performance network-constrained spatial point pattern analysis in Python
Author: FastNSA Project
License: LGPL-2.1-only
Keywords: GIS,spatial,network,point-pattern,K-function
Classifier: License :: OSI Approved :: GNU Lesser General Public License v3 (LGPLv3)
Classifier: Programming Language :: Python :: 3
Classifier: Programming Language :: C++
Classifier: Topic :: Scientific/Engineering :: GIS
Classifier: Topic :: Scientific/Engineering :: Mathematics
Requires-Python: >=3.9
License-File: LICENSE
Requires-Dist: numpy
Requires-Dist: pandas
Requires-Dist: geopandas
Requires-Dist: osmnx
Requires-Dist: shapely
Dynamic: license-file
